PyYPAC/__init__.py
PyYPAC/BPE/__init__.py
PyYPAC/BPE/bpe.py
PyYPAC/DPAC/File.py
PyYPAC/DPAC/__init__.py
PyYPAC/DPAC/export/File.py
PyYPAC/EPAC/File.py
PyYPAC/EPAC/__init__.py
PyYPAC/EPK8/File.py
PyYPAC/EPK8/__init__.py
PyYPAC/MPQ/MPQ.py
PyYPAC/MPQ/__init__.py
PyYPAC/PAC/Data.py
PyYPAC/PAC/__init__.py
PyYPAC/PAC/export/Data.py
PyYPAC/TEX/__init__.py
PyYPAC/TEX/fpac.py
pyypac-1.1.6.dist-info/licenses/LICENSE.txt
pyypac-1.1.6.dist-info/METADATA
pyypac-1.1.6.dist-info/WHEEL
pyypac-1.1.6.dist-info/top_level.txt
pyypac-1.1.6.dist-info/RECORD
