Metadata-Version: 2.4
Name: PyYPAC
Version: 1.1.6
Summary: Package for handling Yuke's PAC DPAC EPAC EPK8 formats (BPE in the works)
Keywords: PAC,WWE,WWF,Yuke's,YUKES,THQ,Video Game
Classifier: Development Status :: 4 - Beta
Classifier: Intended Audience :: Developers
Classifier: Operating System :: Microsoft :: Windows :: Windows 11
Classifier: Programming Language :: Python :: Free Threading
Classifier: Topic :: System :: Filesystems
Classifier: Typing :: Typed
Classifier: Topic :: Games/Entertainment
Classifier: Topic :: File Formats
Classifier: Environment :: Other Environment
Classifier: Natural Language :: English
Requires-Python: >=3.14
License-File: LICENSE.txt
Dynamic: license-file
